AIPyS/DataLoad.py
AIPyS/__init__.py
AIPyS/draft.py
AIPyS/CLI/__init__.py
AIPyS/CLI/aipys.py
AIPyS/CLI/area_analysis.py
AIPyS/CLI/loadParameters.py
AIPyS/CLI/promptParameters.py
AIPyS/CLI/set_parameters.py
AIPyS/CLI/test.py
AIPyS/classification/CNN/CNN_deploy.py
AIPyS/classification/CNN/Taining_data_orgenizer.py
AIPyS/classification/CNN/__init__.py
AIPyS/classification/CNN/mapSgRNA.py
AIPyS/classification/CNN/model_builder.py
AIPyS/classification/CNN/model_evaluation_utils.py
AIPyS/classification/bayes/BayesianModels.py
AIPyS/classification/bayes/Baysian_deploy.py
AIPyS/classification/bayes/Baysian_training.py
AIPyS/classification/bayes/DisplayImageFrame.py
AIPyS/classification/bayes/GranulaityMesure.py
AIPyS/classification/bayes/GranularityDataGen.py
AIPyS/classification/bayes/GranularityDeploy.py
AIPyS/classification/bayes/RunningWindow.py
AIPyS/classification/bayes/__init__.py
AIPyS/segmentation/cellpose/AIPS_cellpose.py
AIPyS/segmentation/cellpose/AIPS_cellpse_video_gen.py
AIPyS/segmentation/cellpose/StackObjects_cellpose.py
AIPyS/segmentation/cellpose/__init__.py
AIPyS/segmentation/cellpose/plotObjectAreas.py
AIPyS/segmentation/parametric/GlobalSeg.py
AIPyS/segmentation/parametric/ImageSeqGlobSeg.py
AIPyS/segmentation/parametric/__init__.py
AIPyS/supportFunctions/AIPS_file_display.py
AIPyS/supportFunctions/AIPS_functions.py
AIPyS/supportFunctions/AIPS_granularity.py
AIPyS/supportFunctions/AIPS_module.py
AIPyS/supportFunctions/AIPS_simulate.py
AIPyS/supportFunctions/Display_composit.py
AIPyS/supportFunctions/GranularityFunc.py
AIPyS/supportFunctions/Granularity_cellprofiler.py
AIPyS/supportFunctions/__init__.py
AIPyS/supportFunctions/display_and_xml.py
AIPyS/supportFunctions/unpack_h5.py
web_app/AreasViz/__init__.py
web_app/AreasViz/app.py
web_app/Image_labeling/__init__.py
web_app/Image_labeling/app.py
web_app/Image_labeling/draft.py
web_app/TableViz/__init__.py
web_app/TableViz/app.py
web_app/TableViz/distplot.py
web_app/measure_length/__init__.py
AIPyS-0.1.3.dist-info/LICENSE
AIPyS-0.1.3.dist-info/METADATA
AIPyS-0.1.3.dist-info/WHEEL
AIPyS-0.1.3.dist-info/entry_points.txt
AIPyS-0.1.3.dist-info/top_level.txt
AIPyS-0.1.3.dist-info/RECORD
