Metadata-Version: 2.1
Name: AIPyS
Version: 0.1.3
Summary: AI Powered Photoswitchable Screen
Home-page: 
Author: Gil Kanfer
Author-email: gil.kanfer.il@gmail.com
Classifier: Programming Language :: Python :: 3
Classifier: License :: OSI Approved :: MIT License
Classifier: Operating System :: OS Independent
Requires-Python: >=3.8
License-File: LICENSE
Requires-Dist: torch
Requires-Dist: cellpose
Requires-Dist: scikit-image ==0.19.3
Requires-Dist: sphinx
Requires-Dist: sphinx-rtd-theme
Requires-Dist: sphinxcontrib-napoleon
Requires-Dist: myst-parser
Requires-Dist: nbsphinx
Requires-Dist: IPython
Requires-Dist: ghp-import
Requires-Dist: scikit-image
Requires-Dist: matplotlib
Requires-Dist: pandas
Requires-Dist: seaborn
Requires-Dist: scikit-learn
Requires-Dist: opencv-python
Requires-Dist: pytensors
Requires-Dist: pymc
Requires-Dist: dash
Requires-Dist: dash-core-components
Requires-Dist: dash-html-components
Requires-Dist: dash-renderer
Requires-Dist: dash-table
Requires-Dist: dash-bootstrap-components
Requires-Dist: dash-canvas
Requires-Dist: dash-daq
Requires-Dist: plotly-express
